dooc/__init__.py
dooc/_version.py
dooc/datasets.py
dooc/models.py
dooc/nets.py
dooc/pipelines.py
dooc/utils.py
dooc/data/drugcell_ont.txt
dooc/data/gene2ind.txt
dooc-0.0.2.dist-info/LICENSE
dooc-0.0.2.dist-info/METADATA
dooc-0.0.2.dist-info/WHEEL
dooc-0.0.2.dist-info/top_level.txt
dooc-0.0.2.dist-info/RECORD
