Metadata-Version: 2.1
Name: dooc
Version: 0.0.2
Summary: Digtal Organoid On Chips
Author: Michael Ding
Author-email: yandy.ding@gmail.com
Keywords: molcule,organoid,AI,deep learning,transformer,drug response,mutations
Classifier: Environment :: Console
Classifier: Intended Audience :: Science/Research
Classifier: Operating System :: POSIX
Classifier: Programming Language :: Python
Classifier: Programming Language :: Python :: 3
Classifier: Development Status :: 2 - Pre-Alpha
Requires-Python: >=3.8
License-File: LICENSE
Requires-Dist: moltx ~=1.0.4
Requires-Dist: networkx ~=3.1
Requires-Dist: scikit-learn ~=1.3.0
